vigenere/__init__.py
vigenere/__main__.py
vigenere/info.txt
vigenere/random.py
vigenere/vigenere.py
vigenere-1.1.0.dist-info/LICENSE
vigenere-1.1.0.dist-info/METADATA
vigenere-1.1.0.dist-info/WHEEL
vigenere-1.1.0.dist-info/entry_points.txt
vigenere-1.1.0.dist-info/top_level.txt
vigenere-1.1.0.dist-info/RECORD
