Metadata-Version: 2.1
Name: vigenere
Version: 1.1.0
Summary: Encrypt strings using Vigenere Cipher
Home-page: https://github.com/GuptaAyush19/Vigenere-Cipher
Author: Ayush Gupta
Author-email: darthvader01502@gmail.com
License: MIT
Platform: UNKNOWN
Classifier: License :: OSI Approved :: MIT License
Classifier: Programming Language :: Python :: 3
Classifier: Programming Language :: Python :: 3.9
